{"foto":"http://aplicaciones004.jne.gob.pe/padron/06/06/01/239822/41502371.JPG","id_hoja_vida":130339,"documento_identidad":"41502371","apellido_paterno":"BENAVIDES","apellido_materno":"GAVIDIA","nombres":"WALTER","organizacion_politica":"ALIANZA PARA EL PROGRESO","cargo_electo":"CONGRESISTA DE LA REPÚBLICA","distrito_postulacion":"CAJAMARCA","educacion":{"basica":true,"primaria":true,"primaria_completa":true,"secundaria":true,"secundaria_completa":true,"universitaria":[{"universidad":"UNIVERSIDAD NACIONAL PEDRO RUIZ GALLO","carrera":"INGENIERÍA CIVIL","bachiller":true,"concluida":true,"titulo":true}],"postgrados":[]},"experiencia_laboral":[{"centro_laboral":"MUNICIPALIDAD DISTRITAL DE CHANCAYBAÑOS","ocupacion":"CONSULTORIAS","desde":"2013","hasta":"2013"},{"centro_laboral":"GERENCIA SUB REGIONAL DE CUTERVO","ocupacion":"GERENTE SUB REGIONAL","desde":"2013","hasta":"2015"},{"centro_laboral":"GOBIERNO REGIONAL DE CAJAMARCA","ocupacion":"ASESOR FAG","desde":"2016","hasta":"2016"},{"centro_laboral":"GERENCIA SUB REGIONAL DE CHOTA","ocupacion":"GERENTE SUB REGIONAL","desde":"2016","hasta":"2017"},{"centro_laboral":"CONSTRUCTORA WB HNOS SRL","ocupacion":"ASISTENTE DE RESIDENTE","desde":"2019","hasta":"HASTA LA ACTUALIDAD"}],"cargos_electos":[],"cargos_partidarios":[],"renuncias":[],"sentencias":{"penales":[],"civiles":[]},"ingresos":[],"inmuebles":[{"tipo":"TERRENO","sunarp":"","autovaluo":10000},{"tipo":"TERRENO","sunarp":"","autovaluo":30000}],"muebles":[],"otros":[],"contraloria":[],"trayectoria":[{"dni":"41502371","eleccion":"ELECCIONES REGIONALES Y MUNICIPALES 2018","lugar":"CAJAMARCA","cargo":"GOBERNADOR REGIONAL","organizacion_politica":"ALIANZA PARA EL PROGRESO","cargo_electo":"NO ELECTO"},{"dni":"41502371","eleccion":"ELECCIONES REGIONALES 2018 2DA VUELTA","lugar":"CAJAMARCA","cargo":"GOBERNADOR REGIONAL","organizacion_politica":"ALIANZA PARA EL PROGRESO","cargo_electo":"NO ELECTO"},{"dni":"41502371","eleccion":"ELECCIONES GENERALES 2016","lugar":"NACION","cargo":"CONGRESISTA","organizacion_politica":"DEMOCRACIA DIRECTA","cargo_electo":"NO ELECTO"}],"website":"http://www.congreso.gob.pe/congresistas2016/WalterBenavides/","bancada":"ALIANZA PARA EL PROGRESO"}