{"foto":"http://aplicaciones004.jne.gob.pe/padron/14/01/42/042295/10144733.JPG","id_hoja_vida":131090,"documento_identidad":"10144733","apellido_paterno":"CASTILLO","apellido_materno":"OLIVA","nombres":"LUIS FELIPE","organizacion_politica":"PODEMOS PERU","cargo_electo":"CONGRESISTA DE LA REPÚBLICA","distrito_postulacion":"LIMA + RESIDENTES EN EL EXTRANJERO","educacion":{"basica":true,"primaria":true,"primaria_completa":true,"secundaria":true,"secundaria_completa":true,"universitaria":[{"universidad":"UNIVERSIDAD PERUANA CAYETANO HEREDIA","carrera":"MEDICINA HUMANA","bachiller":true,"concluida":true,"titulo":true},{"universidad":"UNIVERSIDAD PERUANA CAYETANO HEREDIA","carrera":"ESPECIALIDAD EN GINECOLOGIA Y OBSTETRICIA","bachiller":false,"concluida":true,"titulo":true}],"postgrados":[{"centro_estudios":"UNIVERSIDAD PERUANA CAYETANO HEREDIA","especialidad":"MAESTRIA EN MEDICINA CON MENCIÓN EN GINECOLOGIA Y OBSTETRICIA","grado":"MAESTRO","concluida":true,"egresado":true}]},"experiencia_laboral":[{"centro_laboral":"HOSPITAL MARINO MOLINA SCIPPA-ESSALUD","ocupacion":"MEDICO ASISTENTE GINECO-OBSTETRA","desde":"2010","hasta":"HASTA LA ACTUALIDAD"},{"centro_laboral":"HOSPITAL ALBERTO L. BARTON THOMPSON-CALLAO SALUD SAC","ocupacion":"MEDICO ASISTENTE GINECO-OBSTETRA","desde":"2015","hasta":"2015"},{"centro_laboral":"GESTAR VIDA CENTRO DE MEDICINA MATERNO FETAL FERTILIDAD ASISTIDA Y GINECOLOGIA E.I.R.L.","ocupacion":"GERENTE TITULAR","desde":"2012","hasta":"HASTA LA ACTUALIDAD"},{"centro_laboral":"UNIVERSIDAD PRIVADA SAN JUAN BAUTISTA SEDE HOSPITAL NACIONAL ARZOBISPO LOAYZA","ocupacion":"DOCENTE","desde":"2009","hasta":"2012"}],"cargos_electos":[{"organizacion_politica":"PARTIDO POLÍTICO RENACIMIENTO UNIDO NACIONAL","cargo":"REGIDOR PROVINCIAL","desde":"2011","hasta":"2014"}],"cargos_partidarios":[{"organizacion_politica":"PARTIDO POLÍTICO RENACIMIENTO UNIDO NACIONAL","cargo":"SECRETARIO GENERAL NACIONAL","desde":"2010","hasta":"2017"}],"renuncias":[{"organizacion_politica":"PARTIDO POLÍTICO RENACIMIENTO UNIDO NACIONAL","anio":"2017"}],"sentencias":{"penales":[],"civiles":[]},"ingresos":[{"remuneracion_bruta_anual":{"publico":21797,"privado":168908,"total":190705},"renta_bruta_anual_ejercicio_individual":{"publico":73479,"privado":0,"total":73479},"otros_ingresos":{"publico":0,"privado":40000,"total":40000}}],"inmuebles":[{"tipo":"CASA","sunarp":"43827308","autovaluo":71324},{"tipo":"CASA","sunarp":"43827316","autovaluo":47636},{"tipo":"CASA","sunarp":"12380016","autovaluo":178971}],"muebles":[{"vehiculo":"CAMIONETA","placa":"F0C270 - -","valor":89100},{"vehiculo":"CAMIONETA","placa":"AJZ264 - -","valor":112200}],"otros":[],"contraloria":[],"trayectoria":[{"dni":"10144733","eleccion":"ELECCIONES REGIONALES Y MUNICIPALES 2014","lugar":"LIMA - LIMA - LOS OLIVOS","cargo":"ALCALDE DISTRITAL","organizacion_politica":"SIEMPRE UNIDOS","cargo_electo":"NO ELECTO"},{"dni":"10144733","eleccion":"ELECCIONES REGIONALES Y MUNICIPALES 2018","lugar":"LIMA - LIMA - LOS OLIVOS","cargo":"ALCALDE DISTRITAL","organizacion_politica":"PARTIDO DEMOCRATICO SOMOS PERU","cargo_electo":"NO ELECTO"},{"dni":"10144733","eleccion":"ELECCIONES REGIONALES Y MUNICIPALES 2010","lugar":"LIMA - LIMA","cargo":"REGIDOR PROVINCIAL","organizacion_politica":"SIEMPRE UNIDOS","cargo_electo":"REGIDOR PROVINCIAL"}]}