{"foto":"http://aplicaciones004.jne.gob.pe/padron/14/01/26/230459/44242860.JPG","id_hoja_vida":131196,"documento_identidad":"44242860","apellido_paterno":"LAZO","apellido_materno":"VILLON","nombres":"LESLYE CAROL","organizacion_politica":"ACCION POPULAR","cargo_electo":"CONGRESISTA DE LA REPÚBLICA","distrito_postulacion":"LIMA + RESIDENTES EN EL EXTRANJERO","educacion":{"basica":true,"primaria":true,"primaria_completa":true,"secundaria":true,"secundaria_completa":true,"universitaria":[{"universidad":"UNIVERSIDAD MAYOR DE SAN MARCOS","carrera":"DERECHO Y CIENCIAS POLITICAS","bachiller":true,"concluida":true,"titulo":true}],"postgrados":[]},"experiencia_laboral":[{"centro_laboral":"NOTARIA BANDA GONZALEZ","ocupacion":"ASESORA LEGAL","desde":"2016","hasta":"2018"},{"centro_laboral":"GOBIERNO REGIONAL LORETO","ocupacion":"ASESORA LEGAL","desde":"2013","hasta":"2014"},{"centro_laboral":"NOTARIA SERGIO A DEL CASTILLO","ocupacion":"ASESORA LEGAL","desde":"2007","hasta":"2013"}],"cargos_electos":[],"cargos_partidarios":[],"renuncias":[],"sentencias":{"penales":[],"civiles":[]},"ingresos":[{"remuneracion_bruta_anual":{"publico":0,"privado":6600,"total":6600},"renta_bruta_anual_ejercicio_individual":{"publico":0,"privado":0,"total":0},"otros_ingresos":{"publico":0,"privado":36000,"total":36000}}],"inmuebles":[{"tipo":"INMUEBLE","sunarp":"13443356","autovaluo":100762.11},{"tipo":"INMUEBLE","sunarp":"11060269","autovaluo":108647.7}],"muebles":[{"vehiculo":"CAMIONETA","placa":"D2D020 - AUTOMATICA","valor":60000}],"otros":[{"nombre":"ACCIONES","descripcion":"LAVILL INVESTMENTS EIRL","valor":20000}],"contraloria":[],"trayectoria":[],"website":"http://www.congreso.gob.pe/congresistas2016/LeslyeLazo/","bancada":"ACCIÓN POPULAR"}