{"foto":"http://aplicaciones004.jne.gob.pe/padron/14/01/10/246823/08261544.JPG","id_hoja_vida":131000,"documento_identidad":"08261544","apellido_paterno":"TITO","apellido_materno":"ORTEGA","nombres":"ERWIN","organizacion_politica":"FUERZA POPULAR","cargo_electo":"CONGRESISTA DE LA REPÚBLICA","distrito_postulacion":"JUNIN","educacion":{"basica":true,"primaria":true,"primaria_completa":true,"secundaria":true,"secundaria_completa":true,"universitaria":[{"universidad":"UNIVERSIDAD NACIONAL \"FEDERICO VILLARREAL\"","carrera":"MEDICINA HUMANA","bachiller":true,"concluida":true,"titulo":true},{"universidad":"UNIVERSIDAD NACIONAL\"FEDERICO VILLARREAL\"","carrera":"MEDICINA HUMANA ESPECIALIZACIÓN","bachiller":false,"concluida":true,"titulo":true}],"postgrados":[{"centro_estudios":"UNIVERSIDAD NACIONAL DEL CENTRO DEL PERÚ","especialidad":"DIDÁCTICA UNIVERSITARIA","grado":"MAESTRO","concluida":true,"egresado":true}]},"experiencia_laboral":[{"centro_laboral":"HOSPITAL REGIONAL DOCENTE MATERNO INFANTIL EL CARMEN","ocupacion":"GINECÓLOGO OBSTETRA","desde":"1995","hasta":"2019"}],"cargos_electos":[],"cargos_partidarios":[],"renuncias":[{"organizacion_politica":"PARTIDO POLÍTICO PARTIDO APRISTA PERUANO","anio":"2014"}],"sentencias":{"penales":[],"civiles":[]},"ingresos":[{"remuneracion_bruta_anual":{"publico":90110.91,"privado":129715,"total":219825.91},"renta_bruta_anual_ejercicio_individual":{"publico":0,"privado":0,"total":0},"otros_ingresos":{"publico":0,"privado":0,"total":0}}],"inmuebles":[{"tipo":"DEPARTAMENTO","sunarp":"12355611","autovaluo":3959.84},{"tipo":"TERRENO","sunarp":"11014900","autovaluo":2200},{"tipo":"DEPÓSITO","sunarp":"12355604","autovaluo":2244.67},{"tipo":"COCHERA","sunarp":"12355607","autovaluo":4070.81}],"muebles":[{"vehiculo":"CAMIONETA","placa":"ASD 223 - COLOR AZUL","valor":175000}],"otros":[],"contraloria":[],"trayectoria":[],"website":"http://www.congreso.gob.pe/congresistas2016/ErwinTito/","bancada":"FUERZA POPULAR"}